html2jirawiki/__init__.py
html2jirawiki/html2jirawiki.py
html2jirawiki-1.0.0.dist-info/LICENSE.txt
html2jirawiki-1.0.0.dist-info/METADATA
html2jirawiki-1.0.0.dist-info/RECORD
html2jirawiki-1.0.0.dist-info/WHEEL
html2jirawiki-1.0.0.dist-info/top_level.txt
