Metadata-Version: 2.1
Name: html2jirawiki
Version: 1.0.0
Summary: A sample Python project to convert HTML to JIRA Wiki
Home-page: https://github.com/vikramarsid/html2jirawiki
Author: Vikram Arsid
Author-email: vikramarsid@gmail.com
License: UNKNOWN
Keywords: HTML,JIRA Wiki
Platform: UNKNOWN
Classifier: Development Status :: 5 - Production/Stable
Classifier: Intended Audience :: Developers
Classifier: Topic :: Software Development :: Build Tools
Classifier: License :: OSI Approved :: MIT License
Classifier: Programming Language :: Python :: 2
Classifier: Programming Language :: Python :: 2.7
Requires-Dist: beautifulsoup4
Requires-Dist: six
